install/__init__.py
install-1.3.2.dist-info/LICENSE
install-1.3.2.dist-info/METADATA
install-1.3.2.dist-info/WHEEL
install-1.3.2.dist-info/top_level.txt
install-1.3.2.dist-info/RECORD
